{
    "name": "Thiên Đỉnh TV (00:12 18/03/2026)",
    "groups": [
        {
            "id": "live",
            "name": "🔴 Live",
            "channels": [
                {
                    "id": "ch-218ce297e43e",
                    "name": "⚽ 22:00 17/03 Live +10' Villarreal VS U19 PSG U19 BLV Táo Văn Nghệ",
                    "type": "single",
                    "display": "thumbnail-only",
                    "image": {
                        "url": "https://images.weserv.nl/?url=https://upload.wikimedia.org/wikipedia/tr/f/fc/Villarreal_CF_logo.png&w=200&h=200&fit=contain&output=png&bg=ececec&draw=https://images.weserv.nl/?url=https://upload.wikimedia.org/wikipedia/vi/a/a7/Paris_Saint-Germain_F.C..svg%26w%3D200%26h%3D200%26fit%3Dcontain%26output%3Dpng%26bg%3Dececec,100,0,0,0,0",
                        "display": "contain",
                        "padding": 1,
                        "background_color": "#ececec"
                    },
                    "sources": [
                        {
                            "id": "src-218ce297e43e",
                            "contents": [
                                {
                                    "id": "ct-218ce297e43e",
                                    "streams": [
                                        {
                                            "stream_links": [
                                                {
                                                    "url": "",
                                                    "type": "hls",
                                                    "request_headers": [
                                                        {
                                                            "key": "Referer",
                                                            "value": "https://sv1.thiendinh.live/xem-truc-tiep/bong-da/uefa-youth-league-1758632823554/villarreal-u19-vs-psg-u19.v1MFU3O8PD"
                                                        },
                                                        {
                                                            "key": "User-Agent",
                                                            "value": "Mozilla/5.0"
                                                        }
                                                    ]
                                                }
                                            ]
                                        }
                                    ]
                                }
                            ]
                        }
                    ]
                },
                {
                    "id": "ch-fd9c1ce93b45",
                    "name": "⚽ 03:00 19/03 Liverpool VS Galatasaray BLV Ngọc Hoàng(A Cháo)",
                    "type": "single",
                    "display": "thumbnail-only",
                    "image": {
                        "url": "https://images.weserv.nl/?url=https://ssl.gstatic.com/onebox/media/sports/logos/nGfV05dipbAc7zzojivKew_96x96.png&w=200&h=200&fit=contain&output=png&bg=ececec&draw=https://images.weserv.nl/?url=https://upload.wikimedia.org/wikipedia/commons/f/f6/Galatasaray_Sports_Club_Logo.png%26w%3D200%26h%3D200%26fit%3Dcontain%26output%3Dpng%26bg%3Dececec,100,0,0,0,0",
                        "display": "contain",
                        "padding": 1,
                        "background_color": "#ececec"
                    },
                    "sources": [
                        {
                            "id": "src-fd9c1ce93b45",
                            "contents": [
                                {
                                    "id": "ct-fd9c1ce93b45",
                                    "streams": [
                                        {
                                            "stream_links": [
                                                {
                                                    "url": "",
                                                    "type": "hls",
                                                    "request_headers": [
                                                        {
                                                            "key": "Referer",
                                                            "value": "https://sv1.thiendinh.live/xem-truc-tiep/bong-da/uefa-champions-league-1758631510260/liverpool-vs-galatasaray.f_UGSLgfi1"
                                                        },
                                                        {
                                                            "key": "User-Agent",
                                                            "value": "Mozilla/5.0"
                                                        }
                                                    ]
                                                }
                                            ]
                                        }
                                    ]
                                }
                            ]
                        }
                    ]
                },
                {
                    "id": "ch-416d6f8f36c6",
                    "name": "⚽ 03:00 19/03 Liverpool VS Galatasaray BLV Táo Mèo",
                    "type": "single",
                    "display": "thumbnail-only",
                    "image": {
                        "url": "https://images.weserv.nl/?url=https://ssl.gstatic.com/onebox/media/sports/logos/nGfV05dipbAc7zzojivKew_96x96.png&w=200&h=200&fit=contain&output=png&bg=ececec&draw=https://images.weserv.nl/?url=https://upload.wikimedia.org/wikipedia/commons/f/f6/Galatasaray_Sports_Club_Logo.png%26w%3D200%26h%3D200%26fit%3Dcontain%26output%3Dpng%26bg%3Dececec,100,0,0,0,0",
                        "display": "contain",
                        "padding": 1,
                        "background_color": "#ececec"
                    },
                    "sources": [
                        {
                            "id": "src-416d6f8f36c6",
                            "contents": [
                                {
                                    "id": "ct-416d6f8f36c6",
                                    "streams": [
                                        {
                                            "stream_links": [
                                                {
                                                    "url": "",
                                                    "type": "hls",
                                                    "request_headers": [
                                                        {
                                                            "key": "Referer",
                                                            "value": "https://sv1.thiendinh.live/xem-truc-tiep/bong-da/uefa-champions-league-1758631510260/liverpool-vs-galatasaray.48BcGnOelV"
                                                        },
                                                        {
                                                            "key": "User-Agent",
                                                            "value": "Mozilla/5.0"
                                                        }
                                                    ]
                                                }
                                            ]
                                        }
                                    ]
                                }
                            ]
                        }
                    ]
                }
            ]
        },
        {
            "id": "upcoming",
            "name": "🗓 Sắp diễn ra",
            "channels": [
                {
                    "id": "ch-b8f12352f6b2",
                    "name": "⚽ 00:45 18/03 Sporting VS CPBodo/Glimt BLV Táo Chè",
                    "type": "single",
                    "display": "thumbnail-only",
                    "image": {
                        "url": "https://images.weserv.nl/?url=https://upload.wikimedia.org/wikipedia/vi/3/3e/Sporting_Clube_de_Portugal.png&w=200&h=200&fit=contain&output=png&bg=ececec&draw=https://images.weserv.nl/?url=https://media.api-sports.io/football/teams/327.png%26w%3D200%26h%3D200%26fit%3Dcontain%26output%3Dpng%26bg%3Dececec,100,0,0,0,0",
                        "display": "contain",
                        "padding": 1,
                        "background_color": "#ececec"
                    },
                    "sources": [
                        {
                            "id": "src-b8f12352f6b2",
                            "contents": [
                                {
                                    "id": "ct-b8f12352f6b2",
                                    "streams": [
                                        {
                                            "stream_links": [
                                                {
                                                    "url": "",
                                                    "type": "hls",
                                                    "request_headers": [
                                                        {
                                                            "key": "Referer",
                                                            "value": "https://sv1.thiendinh.live/xem-truc-tiep/bong-da/uefa-champions-league-1758631510260/sporting-cp-vs-bodoglimt.OivfIMKKpk"
                                                        },
                                                        {
                                                            "key": "User-Agent",
                                                            "value": "Mozilla/5.0"
                                                        }
                                                    ]
                                                }
                                            ]
                                        }
                                    ]
                                }
                            ]
                        }
                    ]
                },
                {
                    "id": "ch-4c7fa154287c",
                    "name": "⚽ 03:00 18/03 Arsenal VS Bayer Leverkusen BLV Ngọc Hoàng(A Cháo)",
                    "type": "single",
                    "display": "thumbnail-only",
                    "image": {
                        "url": "https://images.weserv.nl/?url=https://upload.wikimedia.org/wikipedia/vi/5/53/Arsenal_FC.svg&w=200&h=200&fit=contain&output=png&bg=ececec&draw=https://images.weserv.nl/?url=https://upload.wikimedia.org/wikipedia/vi/0/0e/Bayer_04_Leverkusen_logo.png%26w%3D200%26h%3D200%26fit%3Dcontain%26output%3Dpng%26bg%3Dececec,100,0,0,0,0",
                        "display": "contain",
                        "padding": 1,
                        "background_color": "#ececec"
                    },
                    "sources": [
                        {
                            "id": "src-4c7fa154287c",
                            "contents": [
                                {
                                    "id": "ct-4c7fa154287c",
                                    "streams": [
                                        {
                                            "stream_links": [
                                                {
                                                    "url": "",
                                                    "type": "hls",
                                                    "request_headers": [
                                                        {
                                                            "key": "Referer",
                                                            "value": "https://sv1.thiendinh.live/xem-truc-tiep/bong-da/uefa-champions-league-1758631510260/arsenal-vs-bayer-leverkusen.REcK-lm07z"
                                                        },
                                                        {
                                                            "key": "User-Agent",
                                                            "value": "Mozilla/5.0"
                                                        }
                                                    ]
                                                }
                                            ]
                                        }
                                    ]
                                }
                            ]
                        }
                    ]
                },
                {
                    "id": "ch-702418b7fab8",
                    "name": "⚽ 03:00 18/03 Arsenal VS Bayer Leverkusen BLV Táo Văn Hóa(A Bí)",
                    "type": "single",
                    "display": "thumbnail-only",
                    "image": {
                        "url": "https://images.weserv.nl/?url=https://upload.wikimedia.org/wikipedia/vi/5/53/Arsenal_FC.svg&w=200&h=200&fit=contain&output=png&bg=ececec&draw=https://images.weserv.nl/?url=https://upload.wikimedia.org/wikipedia/vi/0/0e/Bayer_04_Leverkusen_logo.png%26w%3D200%26h%3D200%26fit%3Dcontain%26output%3Dpng%26bg%3Dececec,100,0,0,0,0",
                        "display": "contain",
                        "padding": 1,
                        "background_color": "#ececec"
                    },
                    "sources": [
                        {
                            "id": "src-702418b7fab8",
                            "contents": [
                                {
                                    "id": "ct-702418b7fab8",
                                    "streams": [
                                        {
                                            "stream_links": [
                                                {
                                                    "url": "",
                                                    "type": "hls",
                                                    "request_headers": [
                                                        {
                                                            "key": "Referer",
                                                            "value": "https://sv1.thiendinh.live/xem-truc-tiep/bong-da/uefa-champions-league-1758631510260/arsenal-vs-bayer-leverkusen.V6KXjetuC2"
                                                        },
                                                        {
                                                            "key": "User-Agent",
                                                            "value": "Mozilla/5.0"
                                                        }
                                                    ]
                                                }
                                            ]
                                        }
                                    ]
                                }
                            ]
                        }
                    ]
                },
                {
                    "id": "ch-8a951b899809",
                    "name": "⚽ 03:00 18/03 Chelsea Paris VS Saint Germain BLV Táo Chè",
                    "type": "single",
                    "display": "thumbnail-only",
                    "image": {
                        "url": "https://images.weserv.nl/?url=https://ssl.gstatic.com/onebox/media/sports/logos/fhBITrIlbQxhVB6IjxUO6Q_96x96.png&w=200&h=200&fit=contain&output=png&bg=ececec&draw=https://images.weserv.nl/?url=https://ssl.gstatic.com/onebox/media/sports/logos/mcpMspef1hwHwi9qrfp4YQ_96x96.png%26w%3D200%26h%3D200%26fit%3Dcontain%26output%3Dpng%26bg%3Dececec,100,0,0,0,0",
                        "display": "contain",
                        "padding": 1,
                        "background_color": "#ececec"
                    },
                    "sources": [
                        {
                            "id": "src-8a951b899809",
                            "contents": [
                                {
                                    "id": "ct-8a951b899809",
                                    "streams": [
                                        {
                                            "stream_links": [
                                                {
                                                    "url": "",
                                                    "type": "hls",
                                                    "request_headers": [
                                                        {
                                                            "key": "Referer",
                                                            "value": "https://sv1.thiendinh.live/xem-truc-tiep/bong-da/uefa-champions-league-1758631510260/chelsea-vs-paris-saint-germain.jcVkYkflPv"
                                                        },
                                                        {
                                                            "key": "User-Agent",
                                                            "value": "Mozilla/5.0"
                                                        }
                                                    ]
                                                }
                                            ]
                                        }
                                    ]
                                }
                            ]
                        }
                    ]
                },
                {
                    "id": "ch-1436900cc27b",
                    "name": "⚽ 03:00 18/03 Manchester City VS Real Madrid BLV Táo Mèo",
                    "type": "single",
                    "display": "thumbnail-only",
                    "image": {
                        "url": "https://images.weserv.nl/?url=https://upload.wikimedia.org/wikipedia/vi/1/1d/Manchester_City_FC_logo.svg&w=200&h=200&fit=contain&output=png&bg=ececec&draw=https://images.weserv.nl/?url=https://ssl.gstatic.com/onebox/media/sports/logos/Th4fAVAZeCJWRcKoLW7koA_96x96.png%26w%3D200%26h%3D200%26fit%3Dcontain%26output%3Dpng%26bg%3Dececec,100,0,0,0,0",
                        "display": "contain",
                        "padding": 1,
                        "background_color": "#ececec"
                    },
                    "sources": [
                        {
                            "id": "src-1436900cc27b",
                            "contents": [
                                {
                                    "id": "ct-1436900cc27b",
                                    "streams": [
                                        {
                                            "stream_links": [
                                                {
                                                    "url": "",
                                                    "type": "hls",
                                                    "request_headers": [
                                                        {
                                                            "key": "Referer",
                                                            "value": "https://sv1.thiendinh.live/xem-truc-tiep/bong-da/uefa-champions-league-1758631510260/manchester-city-vs-real-madrid.63q9Nt5HSw"
                                                        },
                                                        {
                                                            "key": "User-Agent",
                                                            "value": "Mozilla/5.0"
                                                        }
                                                    ]
                                                }
                                            ]
                                        }
                                    ]
                                }
                            ]
                        }
                    ]
                },
                {
                    "id": "ch-a3882b38908e",
                    "name": "⚽ 03:00 18/03 Manchester City VS Real Madrid BLV Táo Văn Nghệ",
                    "type": "single",
                    "display": "thumbnail-only",
                    "image": {
                        "url": "https://images.weserv.nl/?url=https://upload.wikimedia.org/wikipedia/vi/1/1d/Manchester_City_FC_logo.svg&w=200&h=200&fit=contain&output=png&bg=ececec&draw=https://images.weserv.nl/?url=https://ssl.gstatic.com/onebox/media/sports/logos/Th4fAVAZeCJWRcKoLW7koA_96x96.png%26w%3D200%26h%3D200%26fit%3Dcontain%26output%3Dpng%26bg%3Dececec,100,0,0,0,0",
                        "display": "contain",
                        "padding": 1,
                        "background_color": "#ececec"
                    },
                    "sources": [
                        {
                            "id": "src-a3882b38908e",
                            "contents": [
                                {
                                    "id": "ct-a3882b38908e",
                                    "streams": [
                                        {
                                            "stream_links": [
                                                {
                                                    "url": "",
                                                    "type": "hls",
                                                    "request_headers": [
                                                        {
                                                            "key": "Referer",
                                                            "value": "https://sv1.thiendinh.live/xem-truc-tiep/bong-da/uefa-champions-league-1758631510260/manchester-city-vs-real-madrid.fWmwX1cx_I"
                                                        },
                                                        {
                                                            "key": "User-Agent",
                                                            "value": "Mozilla/5.0"
                                                        }
                                                    ]
                                                }
                                            ]
                                        }
                                    ]
                                }
                            ]
                        }
                    ]
                },
                {
                    "id": "ch-4b644e6fc0c2",
                    "name": "⚽ 16:00 18/03 South Korea VS WJapan W BLV Táo Văn Nghệ",
                    "type": "single",
                    "display": "thumbnail-only",
                    "image": {
                        "url": "https://images.weserv.nl/?url=https://media.api-sports.io/football/teams/1728.png&w=200&h=200&fit=contain&output=png&bg=ececec&draw=https://images.weserv.nl/?url=https://media.api-sports.io/football/teams/1720.png%26w%3D200%26h%3D200%26fit%3Dcontain%26output%3Dpng%26bg%3Dececec,100,0,0,0,0",
                        "display": "contain",
                        "padding": 1,
                        "background_color": "#ececec"
                    },
                    "sources": [
                        {
                            "id": "src-4b644e6fc0c2",
                            "contents": [
                                {
                                    "id": "ct-4b644e6fc0c2",
                                    "streams": [
                                        {
                                            "stream_links": [
                                                {
                                                    "url": "",
                                                    "type": "hls",
                                                    "request_headers": [
                                                        {
                                                            "key": "Referer",
                                                            "value": "https://sv1.thiendinh.live/xem-truc-tiep/bong-da/asian-cup-women.NOPb57w_wj/south-korea-w-vs-japan-w.sDNk9EaUcN"
                                                        },
                                                        {
                                                            "key": "User-Agent",
                                                            "value": "Mozilla/5.0"
                                                        }
                                                    ]
                                                }
                                            ]
                                        }
                                    ]
                                }
                            ]
                        }
                    ]
                },
                {
                    "id": "ch-27fbe05ecd21",
                    "name": "⚽ 17:30 18/03 Pohang Steelers VS FC Seoul BLV Táo Tàu",
                    "type": "single",
                    "display": "thumbnail-only",
                    "image": {
                        "url": "https://images.weserv.nl/?url=https://upload.wikimedia.org/wikipedia/lt/c/cf/Pohang_Steelers_logo.png&w=200&h=200&fit=contain&output=png&bg=ececec&draw=https://images.weserv.nl/?url=https://static.bongda24h.vn/Medias/original/2022/11/09/seoul-0911213928.png%26w%3D200%26h%3D200%26fit%3Dcontain%26output%3Dpng%26bg%3Dececec,100,0,0,0,0",
                        "display": "contain",
                        "padding": 1,
                        "background_color": "#ececec"
                    },
                    "sources": [
                        {
                            "id": "src-27fbe05ecd21",
                            "contents": [
                                {
                                    "id": "ct-27fbe05ecd21",
                                    "streams": [
                                        {
                                            "stream_links": [
                                                {
                                                    "url": "",
                                                    "type": "hls",
                                                    "request_headers": [
                                                        {
                                                            "key": "Referer",
                                                            "value": "https://sv1.thiendinh.live/xem-truc-tiep/bong-da/k-league-1-1758630323713/pohang-steelers-vs-fc-seoul.C5cwFnI3Yu"
                                                        },
                                                        {
                                                            "key": "User-Agent",
                                                            "value": "Mozilla/5.0"
                                                        }
                                                    ]
                                                }
                                            ]
                                        }
                                    ]
                                }
                            ]
                        }
                    ]
                },
                {
                    "id": "ch-c0caf7e9f7a8",
                    "name": "⚽ 18:00 18/03 Da Nang VS Nam Dinh BLV Táo Văn Hóa(A Bí)",
                    "type": "single",
                    "display": "thumbnail-only",
                    "image": {
                        "url": "https://images.weserv.nl/?url=https://media.api-sports.io/football/teams/3669.png&w=200&h=200&fit=contain&output=png&bg=ececec&draw=https://images.weserv.nl/?url=https://media.api-sports.io/football/teams/3674.png%26w%3D200%26h%3D200%26fit%3Dcontain%26output%3Dpng%26bg%3Dececec,100,0,0,0,0",
                        "display": "contain",
                        "padding": 1,
                        "background_color": "#ececec"
                    },
                    "sources": [
                        {
                            "id": "src-c0caf7e9f7a8",
                            "contents": [
                                {
                                    "id": "ct-c0caf7e9f7a8",
                                    "streams": [
                                        {
                                            "stream_links": [
                                                {
                                                    "url": "",
                                                    "type": "hls",
                                                    "request_headers": [
                                                        {
                                                            "key": "Referer",
                                                            "value": "https://sv1.thiendinh.live/xem-truc-tiep/bong-da/cup.V4MxeGjilx/da-nang-vs-nam-dinh.OCI9y7yViE"
                                                        },
                                                        {
                                                            "key": "User-Agent",
                                                            "value": "Mozilla/5.0"
                                                        }
                                                    ]
                                                }
                                            ]
                                        }
                                    ]
                                }
                            ]
                        }
                    ]
                },
                {
                    "id": "ch-bcf5407c1db1",
                    "name": "⚽ 20:00 18/03 Real Madrid U19 VS Sporting CP U19 BLV Táo Mèo",
                    "type": "single",
                    "display": "thumbnail-only",
                    "image": {
                        "url": "https://images.weserv.nl/?url=https://upload.wikimedia.org/wikipedia/en/thumb/5/56/Real_Madrid_CF.svg/960px-Real_Madrid_CF.svg.png&w=200&h=200&fit=contain&output=png&bg=ececec&draw=https://images.weserv.nl/?url=https://media.api-sports.io/football/teams/7997.png%26w%3D200%26h%3D200%26fit%3Dcontain%26output%3Dpng%26bg%3Dececec,100,0,0,0,0",
                        "display": "contain",
                        "padding": 1,
                        "background_color": "#ececec"
                    },
                    "sources": [
                        {
                            "id": "src-bcf5407c1db1",
                            "contents": [
                                {
                                    "id": "ct-bcf5407c1db1",
                                    "streams": [
                                        {
                                            "stream_links": [
                                                {
                                                    "url": "",
                                                    "type": "hls",
                                                    "request_headers": [
                                                        {
                                                            "key": "Referer",
                                                            "value": "https://sv1.thiendinh.live/xem-truc-tiep/bong-da/uefa-youth-league-1758632823554/real-madrid-u19-vs-sporting-cp-u19.z1szbmBLbN"
                                                        },
                                                        {
                                                            "key": "User-Agent",
                                                            "value": "Mozilla/5.0"
                                                        }
                                                    ]
                                                }
                                            ]
                                        }
                                    ]
                                }
                            ]
                        }
                    ]
                },
                {
                    "id": "ch-a1cc5744e8b8",
                    "name": "⚽ 21:00 18/03 Super League Johor VS Darul Takzim FCPdrm BLV Táo Chè",
                    "type": "single",
                    "display": "thumbnail-only",
                    "image": {
                        "url": "https://images.weserv.nl/?url=https://media.api-sports.io/football/teams/2523.png&w=200&h=200&fit=contain&output=png&bg=ececec&draw=https://images.weserv.nl/?url=https://encrypted-tbn0.gstatic.com/images%3Fq%3Dtbn:ANd9GcRpT12aHAUOIHMXo5zDCYG6YNxvMki9rMQ8CA%26s%26w%3D200%26h%3D200%26fit%3Dcontain%26output%3Dpng%26bg%3Dececec,100,0,0,0,0",
                        "display": "contain",
                        "padding": 1,
                        "background_color": "#ececec"
                    },
                    "sources": [
                        {
                            "id": "src-a1cc5744e8b8",
                            "contents": [
                                {
                                    "id": "ct-a1cc5744e8b8",
                                    "streams": [
                                        {
                                            "stream_links": [
                                                {
                                                    "url": "",
                                                    "type": "hls",
                                                    "request_headers": [
                                                        {
                                                            "key": "Referer",
                                                            "value": "https://sv1.thiendinh.live/xem-truc-tiep/bong-da/super-league.LiecRmJhZc/johor-darul-takzim-fc-vs-pdrm.vAKczmiedd"
                                                        },
                                                        {
                                                            "key": "User-Agent",
                                                            "value": "Mozilla/5.0"
                                                        }
                                                    ]
                                                }
                                            ]
                                        }
                                    ]
                                }
                            ]
                        }
                    ]
                },
                {
                    "id": "ch-824d802be0a8",
                    "name": "⚽ 22:30 18/03 SC Braga VS Ferencvarosi TC BLV Ngọc Hoàng(A Cháo)",
                    "type": "single",
                    "display": "thumbnail-only",
                    "image": {
                        "url": "https://images.weserv.nl/?url=https://upload.wikimedia.org/wikipedia/en/7/79/S.C._Braga_logo.svg&w=200&h=200&fit=contain&output=png&bg=ececec&draw=https://images.weserv.nl/?url=https://media.api-sports.io/football/teams/651.png%26w%3D200%26h%3D200%26fit%3Dcontain%26output%3Dpng%26bg%3Dececec,100,0,0,0,0",
                        "display": "contain",
                        "padding": 1,
                        "background_color": "#ececec"
                    },
                    "sources": [
                        {
                            "id": "src-824d802be0a8",
                            "contents": [
                                {
                                    "id": "ct-824d802be0a8",
                                    "streams": [
                                        {
                                            "stream_links": [
                                                {
                                                    "url": "",
                                                    "type": "hls",
                                                    "request_headers": [
                                                        {
                                                            "key": "Referer",
                                                            "value": "https://sv1.thiendinh.live/xem-truc-tiep/bong-da/uefa-europa-league-1758631216599/sc-braga-vs-ferencvarosi-tc.CQh-3I514b"
                                                        },
                                                        {
                                                            "key": "User-Agent",
                                                            "value": "Mozilla/5.0"
                                                        }
                                                    ]
                                                }
                                            ]
                                        }
                                    ]
                                }
                            ]
                        }
                    ]
                },
                {
                    "id": "ch-31dab592b95c",
                    "name": "⚽ 00:45 19/03 Barcelona VS Newcastle BLV Táo Văn Hóa(A Bí)",
                    "type": "single",
                    "display": "thumbnail-only",
                    "image": {
                        "url": "https://images.weserv.nl/?url=https://upload.wikimedia.org/wikipedia/vi/9/91/FC_Barcelona_logo.svg&w=200&h=200&fit=contain&output=png&bg=ececec&draw=https://images.weserv.nl/?url=https://media.api-sports.io/football/teams/34.png%26w%3D200%26h%3D200%26fit%3Dcontain%26output%3Dpng%26bg%3Dececec,100,0,0,0,0",
                        "display": "contain",
                        "padding": 1,
                        "background_color": "#ececec"
                    },
                    "sources": [
                        {
                            "id": "src-31dab592b95c",
                            "contents": [
                                {
                                    "id": "ct-31dab592b95c",
                                    "streams": [
                                        {
                                            "stream_links": [
                                                {
                                                    "url": "",
                                                    "type": "hls",
                                                    "request_headers": [
                                                        {
                                                            "key": "Referer",
                                                            "value": "https://sv1.thiendinh.live/xem-truc-tiep/bong-da/uefa-champions-league-1758631510260/barcelona-vs-newcastle.VRNPC3az-i"
                                                        },
                                                        {
                                                            "key": "User-Agent",
                                                            "value": "Mozilla/5.0"
                                                        }
                                                    ]
                                                }
                                            ]
                                        }
                                    ]
                                }
                            ]
                        }
                    ]
                },
                {
                    "id": "ch-b75169644012",
                    "name": "⚽ 00:45 19/03 Barcelona VS Newcastle BLV Táo Văn Nghệ",
                    "type": "single",
                    "display": "thumbnail-only",
                    "image": {
                        "url": "https://images.weserv.nl/?url=https://upload.wikimedia.org/wikipedia/vi/9/91/FC_Barcelona_logo.svg&w=200&h=200&fit=contain&output=png&bg=ececec&draw=https://images.weserv.nl/?url=https://media.api-sports.io/football/teams/34.png%26w%3D200%26h%3D200%26fit%3Dcontain%26output%3Dpng%26bg%3Dececec,100,0,0,0,0",
                        "display": "contain",
                        "padding": 1,
                        "background_color": "#ececec"
                    },
                    "sources": [
                        {
                            "id": "src-b75169644012",
                            "contents": [
                                {
                                    "id": "ct-b75169644012",
                                    "streams": [
                                        {
                                            "stream_links": [
                                                {
                                                    "url": "",
                                                    "type": "hls",
                                                    "request_headers": [
                                                        {
                                                            "key": "Referer",
                                                            "value": "https://sv1.thiendinh.live/xem-truc-tiep/bong-da/uefa-champions-league-1758631510260/barcelona-vs-newcastle.gL7tKnwxdb"
                                                        },
                                                        {
                                                            "key": "User-Agent",
                                                            "value": "Mozilla/5.0"
                                                        }
                                                    ]
                                                }
                                            ]
                                        }
                                    ]
                                }
                            ]
                        }
                    ]
                },
                {
                    "id": "ch-56e9decc05ba",
                    "name": "⚽ 03:00 19/03 Bayern VS München Atalanta BLV Táo Tàu",
                    "type": "single",
                    "display": "thumbnail-only",
                    "image": {
                        "url": "https://images.weserv.nl/?url=https://media.api-sports.io/football/teams/157.png&w=200&h=200&fit=contain&output=png&bg=ececec&draw=https://images.weserv.nl/?url=https://upload.wikimedia.org/wikipedia/vi/5/59/AtalantaBC.png%26w%3D200%26h%3D200%26fit%3Dcontain%26output%3Dpng%26bg%3Dececec,100,0,0,0,0",
                        "display": "contain",
                        "padding": 1,
                        "background_color": "#ececec"
                    },
                    "sources": [
                        {
                            "id": "src-56e9decc05ba",
                            "contents": [
                                {
                                    "id": "ct-56e9decc05ba",
                                    "streams": [
                                        {
                                            "stream_links": [
                                                {
                                                    "url": "",
                                                    "type": "hls",
                                                    "request_headers": [
                                                        {
                                                            "key": "Referer",
                                                            "value": "https://sv1.thiendinh.live/xem-truc-tiep/bong-da/uefa-champions-league-1758631510260/bayern-munchen-vs-atalanta.O0NsFnpv2E"
                                                        },
                                                        {
                                                            "key": "User-Agent",
                                                            "value": "Mozilla/5.0"
                                                        }
                                                    ]
                                                }
                                            ]
                                        }
                                    ]
                                }
                            ]
                        }
                    ]
                },
                {
                    "id": "ch-0143aa46b080",
                    "name": "⚽ 03:00 19/03 Tottenham VS Atletico Madrid BLV Táo Chè",
                    "type": "single",
                    "display": "thumbnail-only",
                    "image": {
                        "url": "https://images.weserv.nl/?url=https://media.api-sports.io/football/teams/47.png&w=200&h=200&fit=contain&output=png&bg=ececec&draw=https://images.weserv.nl/?url=https://upload.wikimedia.org/wikipedia/en/f/f9/Atletico_Madrid_Logo_2024.svg%26w%3D200%26h%3D200%26fit%3Dcontain%26output%3Dpng%26bg%3Dececec,100,0,0,0,0",
                        "display": "contain",
                        "padding": 1,
                        "background_color": "#ececec"
                    },
                    "sources": [
                        {
                            "id": "src-0143aa46b080",
                            "contents": [
                                {
                                    "id": "ct-0143aa46b080",
                                    "streams": [
                                        {
                                            "stream_links": [
                                                {
                                                    "url": "",
                                                    "type": "hls",
                                                    "request_headers": [
                                                        {
                                                            "key": "Referer",
                                                            "value": "https://sv1.thiendinh.live/xem-truc-tiep/bong-da/uefa-champions-league-1758631510260/tottenham-vs-atletico-madrid.7LwSRnUOpt"
                                                        },
                                                        {
                                                            "key": "User-Agent",
                                                            "value": "Mozilla/5.0"
                                                        }
                                                    ]
                                                }
                                            ]
                                        }
                                    ]
                                }
                            ]
                        }
                    ]
                },
                {
                    "id": "ch-a23c245890db",
                    "name": "⚽ 06:00 19/03 CONCACAF Inter VS Miami Nashville SC BLV Táo Văn Nghệ",
                    "type": "single",
                    "display": "thumbnail-only",
                    "image": {
                        "url": "https://images.weserv.nl/?url=https://encrypted-tbn0.gstatic.com/images?q=tbn:ANd9GcSudffqD2g0jjQWUuaVhdEmUDtpntLzckzVLg&s&w=200&h=200&fit=contain&output=png&bg=ececec&draw=https://images.weserv.nl/?url=https://encrypted-tbn0.gstatic.com/images%3Fq%3Dtbn:ANd9GcSIaJhLFN_ZTYSKnj3jf05R3tqKb9WFWROGxw%26s%26w%3D200%26h%3D200%26fit%3Dcontain%26output%3Dpng%26bg%3Dececec,100,0,0,0,0",
                        "display": "contain",
                        "padding": 1,
                        "background_color": "#ececec"
                    },
                    "sources": [
                        {
                            "id": "src-a23c245890db",
                            "contents": [
                                {
                                    "id": "ct-a23c245890db",
                                    "streams": [
                                        {
                                            "stream_links": [
                                                {
                                                    "url": "",
                                                    "type": "hls",
                                                    "request_headers": [
                                                        {
                                                            "key": "Referer",
                                                            "value": "https://sv1.thiendinh.live/xem-truc-tiep/bong-da/concacaf-champions-league.ukl6KjCFTr/inter-miami-vs-nashville-sc.CqdUL_IisN"
                                                        },
                                                        {
                                                            "key": "User-Agent",
                                                            "value": "Mozilla/5.0"
                                                        }
                                                    ]
                                                }
                                            ]
                                        }
                                    ]
                                }
                            ]
                        }
                    ]
                },
                {
                    "id": "ch-218ce297e43e",
                    "name": "⚽ 22:00 17/03 BLV Táo Văn Nghệ Villarreal U19 KXD VS 'PSG U19 BLV Táo Văn NghệTrực tiếp BLV Táo Văn Nghệ22:00 17/03UEFA Youth LeagueVillarreal U19KXD0-0---'PSG U19 BLV Táo Văn NghệTrực tiếp",
                    "type": "single",
                    "display": "thumbnail-only",
                    "image": {
                        "url": "https://images.weserv.nl/?url=https://i.postimg.cc/28gYpktt/signal-2026-02-26-134325.jpg&w=200&h=200&fit=contain&output=png&bg=ececec&draw=https://images.weserv.nl/?url=https://upload.wikimedia.org/wikipedia/tr/f/fc/Villarreal_CF_logo.png%26w%3D200%26h%3D200%26fit%3Dcontain%26output%3Dpng%26bg%3Dececec,100,0,0,0,0",
                        "display": "contain",
                        "padding": 1,
                        "background_color": "#ececec"
                    },
                    "sources": [
                        {
                            "id": "src-218ce297e43e",
                            "contents": [
                                {
                                    "id": "ct-218ce297e43e",
                                    "streams": [
                                        {
                                            "stream_links": [
                                                {
                                                    "url": "",
                                                    "type": "hls",
                                                    "request_headers": [
                                                        {
                                                            "key": "Referer",
                                                            "value": "https://sv1.thiendinh.live/xem-truc-tiep/bong-da/uefa-youth-league-1758632823554/villarreal-u19-vs-psg-u19.v1MFU3O8PD"
                                                        },
                                                        {
                                                            "key": "User-Agent",
                                                            "value": "Mozilla/5.0"
                                                        }
                                                    ]
                                                }
                                            ]
                                        }
                                    ]
                                }
                            ]
                        }
                    ]
                }
            ]
        }
    ]
}
