{
    "name": "Thiên Đỉnh TV (19:00 26/03/2026)",
    "image": {
        "url": "https://encrypted-tbn0.gstatic.com/images?q=tbn:ANd9GcTsJSuLHF9klemrEvihd_wyrOc0DkdxHcS9Kw&s"
    },
    "groups": [
        {
            "id": "live",
            "name": "🔴 Live",
            "channels": [
                {
                    "id": "ch-ef1addb71992",
                    "name": "⚽ 17:30 26/03 Afghanistan VS Myanmar BLV Táo Chè",
                    "type": "single",
                    "display": "thumbnail-only",
                    "image": {
                        "url": "https://raw.githubusercontent.com/sanghvtac/bonglau/refs/heads/main/thumbs/ef1addb71992.png",
                        "display": "contain",
                        "padding": 1,
                        "background_color": "#ececec"
                    },
                    "sources": [
                        {
                            "id": "src-ef1addb71992",
                            "contents": [
                                {
                                    "id": "ct-ef1addb71992",
                                    "streams": [
                                        {
                                            "stream_links": [
                                                {
                                                    "url": "https://tdlive.zlylive.com/live/tdtv_blv_taoche/playlist.m3u8",
                                                    "type": "hls",
                                                    "request_headers": [
                                                        {
                                                            "key": "Referer",
                                                            "value": "https://sv1.thiendinh.live/xem-truc-tiep/bong-da/asian-cup-qualification.yDCAoP1m8s/afghanistan-vs-myanmar.6An-HJpf8s"
                                                        },
                                                        {
                                                            "key": "User-Agent",
                                                            "value": "Mozilla/5.0"
                                                        }
                                                    ]
                                                }
                                            ]
                                        }
                                    ]
                                }
                            ]
                        }
                    ]
                },
                {
                    "id": "ch-4a94518fdd31",
                    "name": "⚽ 19:00 26/03 Vietnam VS Bangladesh BLV Ngọc Hoàng(A Cháo)",
                    "type": "single",
                    "display": "thumbnail-only",
                    "image": {
                        "url": "https://raw.githubusercontent.com/sanghvtac/bonglau/refs/heads/main/thumbs/4a94518fdd31.png",
                        "display": "contain",
                        "padding": 1,
                        "background_color": "#ececec"
                    },
                    "sources": [
                        {
                            "id": "src-4a94518fdd31",
                            "contents": [
                                {
                                    "id": "ct-4a94518fdd31",
                                    "streams": [
                                        {
                                            "stream_links": [
                                                {
                                                    "url": "https://w9lt1225.edgemaxcdn.org/live/tdtv_blv_ngochoang/playlist.m3u8",
                                                    "type": "hls",
                                                    "request_headers": [
                                                        {
                                                            "key": "Referer",
                                                            "value": "https://sv1.thiendinh.live/xem-truc-tiep/bong-da/friendlies.lfpzLJ0DhW/vietnam-vs-bangladesh.kEVUZXSRSh"
                                                        },
                                                        {
                                                            "key": "User-Agent",
                                                            "value": "Mozilla/5.0"
                                                        }
                                                    ]
                                                }
                                            ]
                                        }
                                    ]
                                }
                            ]
                        }
                    ]
                }
            ]
        },
        {
            "id": "upcoming",
            "name": "🗓 Sắp diễn ra",
            "channels": [
                {
                    "id": "ch-e9872433ac4b",
                    "name": "⚽ 21:00 26/03 Famalicão U23 VS Sporting CP U23 BLV Táo Văn Hóa(A Bí)",
                    "type": "single",
                    "display": "thumbnail-only",
                    "image": {
                        "url": "https://raw.githubusercontent.com/sanghvtac/bonglau/refs/heads/main/thumbs/e9872433ac4b.png",
                        "display": "contain",
                        "padding": 1,
                        "background_color": "#ececec"
                    },
                    "sources": [
                        {
                            "id": "src-e9872433ac4b",
                            "contents": [
                                {
                                    "id": "ct-e9872433ac4b",
                                    "streams": [
                                        {
                                            "stream_links": [
                                                {
                                                    "url": "",
                                                    "type": "hls",
                                                    "request_headers": [
                                                        {
                                                            "key": "Referer",
                                                            "value": "https://sv1.thiendinh.live/xem-truc-tiep/bong-da/liga-revelacao-u23.MvppmD0g0z/famalicao-u23-vs-sporting-cp-u23.hEhKarIqPC"
                                                        },
                                                        {
                                                            "key": "User-Agent",
                                                            "value": "Mozilla/5.0"
                                                        }
                                                    ]
                                                }
                                            ]
                                        }
                                    ]
                                }
                            ]
                        }
                    ]
                },
                {
                    "id": "ch-fc75d14aaedc",
                    "name": "⚽ 21:30 26/03 Tanzania VS Liechtenstein BLV Táo Mèo",
                    "type": "single",
                    "display": "thumbnail-only",
                    "image": {
                        "url": "https://raw.githubusercontent.com/sanghvtac/bonglau/refs/heads/main/thumbs/fc75d14aaedc.png",
                        "display": "contain",
                        "padding": 1,
                        "background_color": "#ececec"
                    },
                    "sources": [
                        {
                            "id": "src-fc75d14aaedc",
                            "contents": [
                                {
                                    "id": "ct-fc75d14aaedc",
                                    "streams": [
                                        {
                                            "stream_links": [
                                                {
                                                    "url": "",
                                                    "type": "hls",
                                                    "request_headers": [
                                                        {
                                                            "key": "Referer",
                                                            "value": "https://sv1.thiendinh.live/xem-truc-tiep/bong-da/fifa-series.bbsXDeu2QO/tanzania-vs-liechtenstein.HQrtMyugei"
                                                        },
                                                        {
                                                            "key": "User-Agent",
                                                            "value": "Mozilla/5.0"
                                                        }
                                                    ]
                                                }
                                            ]
                                        }
                                    ]
                                }
                            ]
                        }
                    ]
                },
                {
                    "id": "ch-af2f96f0ade7",
                    "name": "⚽ 22:00 26/03 Moldova VS Lithuania BLV Táo Tàu",
                    "type": "single",
                    "display": "thumbnail-only",
                    "image": {
                        "url": "https://raw.githubusercontent.com/sanghvtac/bonglau/refs/heads/main/thumbs/af2f96f0ade7.png",
                        "display": "contain",
                        "padding": 1,
                        "background_color": "#ececec"
                    },
                    "sources": [
                        {
                            "id": "src-af2f96f0ade7",
                            "contents": [
                                {
                                    "id": "ct-af2f96f0ade7",
                                    "streams": [
                                        {
                                            "stream_links": [
                                                {
                                                    "url": "",
                                                    "type": "hls",
                                                    "request_headers": [
                                                        {
                                                            "key": "Referer",
                                                            "value": "https://sv1.thiendinh.live/xem-truc-tiep/bong-da/friendlies.lfpzLJ0DhW/moldova-vs-lithuania.WwzBYcUoZK"
                                                        },
                                                        {
                                                            "key": "User-Agent",
                                                            "value": "Mozilla/5.0"
                                                        }
                                                    ]
                                                }
                                            ]
                                        }
                                    ]
                                }
                            ]
                        }
                    ]
                },
                {
                    "id": "ch-911be029352e",
                    "name": "⚽ 22:45 26/03 Germany U20 VS Czech Republic BLV Táo Thiên Vương",
                    "type": "single",
                    "display": "thumbnail-only",
                    "image": {
                        "url": "https://raw.githubusercontent.com/sanghvtac/bonglau/refs/heads/main/thumbs/911be029352e.png",
                        "display": "contain",
                        "padding": 1,
                        "background_color": "#ececec"
                    },
                    "sources": [
                        {
                            "id": "src-911be029352e",
                            "contents": [
                                {
                                    "id": "ct-911be029352e",
                                    "streams": [
                                        {
                                            "stream_links": [
                                                {
                                                    "url": "",
                                                    "type": "hls",
                                                    "request_headers": [
                                                        {
                                                            "key": "Referer",
                                                            "value": "https://sv1.thiendinh.live/xem-truc-tiep/bong-da/u20-elite-league.FUqeFnSMnm/germany-u20-vs-czech-republic-u20.aIGCJTrfeH"
                                                        },
                                                        {
                                                            "key": "User-Agent",
                                                            "value": "Mozilla/5.0"
                                                        }
                                                    ]
                                                }
                                            ]
                                        }
                                    ]
                                }
                            ]
                        }
                    ]
                },
                {
                    "id": "ch-99e5282d8f73",
                    "name": "⚽ 00:00 27/03 Malta VS Luxembourg BLV Táo Văn Nghệ",
                    "type": "single",
                    "display": "thumbnail-only",
                    "image": {
                        "url": "https://raw.githubusercontent.com/sanghvtac/bonglau/refs/heads/main/thumbs/99e5282d8f73.png",
                        "display": "contain",
                        "padding": 1,
                        "background_color": "#ececec"
                    },
                    "sources": [
                        {
                            "id": "src-99e5282d8f73",
                            "contents": [
                                {
                                    "id": "ct-99e5282d8f73",
                                    "streams": [
                                        {
                                            "stream_links": [
                                                {
                                                    "url": "",
                                                    "type": "hls",
                                                    "request_headers": [
                                                        {
                                                            "key": "Referer",
                                                            "value": "https://sv1.thiendinh.live/xem-truc-tiep/bong-da/uefa-nations-league-1764651191437/malta-vs-luxembourg.CYd0KaYcfQ"
                                                        },
                                                        {
                                                            "key": "User-Agent",
                                                            "value": "Mozilla/5.0"
                                                        }
                                                    ]
                                                }
                                            ]
                                        }
                                    ]
                                }
                            ]
                        }
                    ]
                },
                {
                    "id": "ch-4aee5915227a",
                    "name": "⚽ 00:00 27/03 Türkiye VS Romania BLV Táo Mèo",
                    "type": "single",
                    "display": "thumbnail-only",
                    "image": {
                        "url": "https://raw.githubusercontent.com/sanghvtac/bonglau/refs/heads/main/thumbs/4aee5915227a.png",
                        "display": "contain",
                        "padding": 1,
                        "background_color": "#ececec"
                    },
                    "sources": [
                        {
                            "id": "src-4aee5915227a",
                            "contents": [
                                {
                                    "id": "ct-4aee5915227a",
                                    "streams": [
                                        {
                                            "stream_links": [
                                                {
                                                    "url": "",
                                                    "type": "hls",
                                                    "request_headers": [
                                                        {
                                                            "key": "Referer",
                                                            "value": "https://sv1.thiendinh.live/xem-truc-tiep/bong-da/world-cup-qualification-europe.Yj2rkxo5_t/turkiye-vs-romania.Q9XJx5L938"
                                                        },
                                                        {
                                                            "key": "User-Agent",
                                                            "value": "Mozilla/5.0"
                                                        }
                                                    ]
                                                }
                                            ]
                                        }
                                    ]
                                }
                            ]
                        }
                    ]
                },
                {
                    "id": "ch-d1b064861665",
                    "name": "⚽ 02:45 27/03 Czech Republic VS Rep. Of Ireland BLV Táo Tàu",
                    "type": "single",
                    "display": "thumbnail-only",
                    "image": {
                        "url": "https://raw.githubusercontent.com/sanghvtac/bonglau/refs/heads/main/thumbs/d1b064861665.png",
                        "display": "contain",
                        "padding": 1,
                        "background_color": "#ececec"
                    },
                    "sources": [
                        {
                            "id": "src-d1b064861665",
                            "contents": [
                                {
                                    "id": "ct-d1b064861665",
                                    "streams": [
                                        {
                                            "stream_links": [
                                                {
                                                    "url": "",
                                                    "type": "hls",
                                                    "request_headers": [
                                                        {
                                                            "key": "Referer",
                                                            "value": "https://sv1.thiendinh.live/xem-truc-tiep/bong-da/world-cup-qualification-europe.Yj2rkxo5_t/czech-republic-vs-rep-of-ireland.1RRyyUA4h3"
                                                        },
                                                        {
                                                            "key": "User-Agent",
                                                            "value": "Mozilla/5.0"
                                                        }
                                                    ]
                                                }
                                            ]
                                        }
                                    ]
                                }
                            ]
                        }
                    ]
                },
                {
                    "id": "ch-0a593c9bac8a",
                    "name": "⚽ 02:45 27/03 Denmark VS FYR Macedonia BLV Táo Chè",
                    "type": "single",
                    "display": "thumbnail-only",
                    "image": {
                        "url": "https://raw.githubusercontent.com/sanghvtac/bonglau/refs/heads/main/thumbs/0a593c9bac8a.png",
                        "display": "contain",
                        "padding": 1,
                        "background_color": "#ececec"
                    },
                    "sources": [
                        {
                            "id": "src-0a593c9bac8a",
                            "contents": [
                                {
                                    "id": "ct-0a593c9bac8a",
                                    "streams": [
                                        {
                                            "stream_links": [
                                                {
                                                    "url": "",
                                                    "type": "hls",
                                                    "request_headers": [
                                                        {
                                                            "key": "Referer",
                                                            "value": "https://sv1.thiendinh.live/xem-truc-tiep/bong-da/world-cup-qualification-europe.Yj2rkxo5_t/denmark-vs-fyr-macedonia.62luY92hnV"
                                                        },
                                                        {
                                                            "key": "User-Agent",
                                                            "value": "Mozilla/5.0"
                                                        }
                                                    ]
                                                }
                                            ]
                                        }
                                    ]
                                }
                            ]
                        }
                    ]
                },
                {
                    "id": "ch-2835fa4ac522",
                    "name": "⚽ 02:45 27/03 Italy VS Northern Ireland BLV Ngọc Hoàng(A Cháo)",
                    "type": "single",
                    "display": "thumbnail-only",
                    "image": {
                        "url": "https://raw.githubusercontent.com/sanghvtac/bonglau/refs/heads/main/thumbs/2835fa4ac522.png",
                        "display": "contain",
                        "padding": 1,
                        "background_color": "#ececec"
                    },
                    "sources": [
                        {
                            "id": "src-2835fa4ac522",
                            "contents": [
                                {
                                    "id": "ct-2835fa4ac522",
                                    "streams": [
                                        {
                                            "stream_links": [
                                                {
                                                    "url": "",
                                                    "type": "hls",
                                                    "request_headers": [
                                                        {
                                                            "key": "Referer",
                                                            "value": "https://sv1.thiendinh.live/xem-truc-tiep/bong-da/world-cup-qualification-europe.Yj2rkxo5_t/italy-vs-northern-ireland.sPXyhGdRAd"
                                                        },
                                                        {
                                                            "key": "User-Agent",
                                                            "value": "Mozilla/5.0"
                                                        }
                                                    ]
                                                }
                                            ]
                                        }
                                    ]
                                }
                            ]
                        }
                    ]
                },
                {
                    "id": "ch-72c9cf7c3d9a",
                    "name": "⚽ 02:45 27/03 Poland VS Albania BLV Táo Văn Hóa(A Bí)",
                    "type": "single",
                    "display": "thumbnail-only",
                    "image": {
                        "url": "https://raw.githubusercontent.com/sanghvtac/bonglau/refs/heads/main/thumbs/72c9cf7c3d9a.png",
                        "display": "contain",
                        "padding": 1,
                        "background_color": "#ececec"
                    },
                    "sources": [
                        {
                            "id": "src-72c9cf7c3d9a",
                            "contents": [
                                {
                                    "id": "ct-72c9cf7c3d9a",
                                    "streams": [
                                        {
                                            "stream_links": [
                                                {
                                                    "url": "",
                                                    "type": "hls",
                                                    "request_headers": [
                                                        {
                                                            "key": "Referer",
                                                            "value": "https://sv1.thiendinh.live/xem-truc-tiep/bong-da/world-cup-qualification-europe.Yj2rkxo5_t/poland-vs-albania.rXTM42BafU"
                                                        },
                                                        {
                                                            "key": "User-Agent",
                                                            "value": "Mozilla/5.0"
                                                        }
                                                    ]
                                                }
                                            ]
                                        }
                                    ]
                                }
                            ]
                        }
                    ]
                },
                {
                    "id": "ch-ca95fa56c30f",
                    "name": "⚽ 02:45 27/03 Ukraine VS Sweden BLV Táo Thiên Vương",
                    "type": "single",
                    "display": "thumbnail-only",
                    "image": {
                        "url": "https://raw.githubusercontent.com/sanghvtac/bonglau/refs/heads/main/thumbs/ca95fa56c30f.png",
                        "display": "contain",
                        "padding": 1,
                        "background_color": "#ececec"
                    },
                    "sources": [
                        {
                            "id": "src-ca95fa56c30f",
                            "contents": [
                                {
                                    "id": "ct-ca95fa56c30f",
                                    "streams": [
                                        {
                                            "stream_links": [
                                                {
                                                    "url": "",
                                                    "type": "hls",
                                                    "request_headers": [
                                                        {
                                                            "key": "Referer",
                                                            "value": "https://sv1.thiendinh.live/xem-truc-tiep/bong-da/world-cup-qualification-europe.Yj2rkxo5_t/ukraine-vs-sweden.fxLUvlUnvk"
                                                        },
                                                        {
                                                            "key": "User-Agent",
                                                            "value": "Mozilla/5.0"
                                                        }
                                                    ]
                                                }
                                            ]
                                        }
                                    ]
                                }
                            ]
                        }
                    ]
                },
                {
                    "id": "ch-3c86ef77d552",
                    "name": "⚽ 03:00 27/03 Brazil VS France BLV Táo Văn Nghệ",
                    "type": "single",
                    "display": "thumbnail-only",
                    "image": {
                        "url": "https://raw.githubusercontent.com/sanghvtac/bonglau/refs/heads/main/thumbs/3c86ef77d552.png",
                        "display": "contain",
                        "padding": 1,
                        "background_color": "#ececec"
                    },
                    "sources": [
                        {
                            "id": "src-3c86ef77d552",
                            "contents": [
                                {
                                    "id": "ct-3c86ef77d552",
                                    "streams": [
                                        {
                                            "stream_links": [
                                                {
                                                    "url": "",
                                                    "type": "hls",
                                                    "request_headers": [
                                                        {
                                                            "key": "Referer",
                                                            "value": "https://sv1.thiendinh.live/xem-truc-tiep/bong-da/friendlies.lfpzLJ0DhW/brazil-vs-france.wMsYa3wOQv"
                                                        },
                                                        {
                                                            "key": "User-Agent",
                                                            "value": "Mozilla/5.0"
                                                        }
                                                    ]
                                                }
                                            ]
                                        }
                                    ]
                                }
                            ]
                        }
                    ]
                },
                {
                    "id": "ch-4a94518fdd31",
                    "name": "⚽ 19:00 26/03 BLV Ngọc Hoàng(A Cháo)FriendliesVietnamKXD0-0---'BangladeshBLV VS Ngọc Hoàng(A Cháo)Trực tiếp BLV Ngọc Hoàng(A Cháo)12:00 26/03FriendliesVietnamKXD0-0---'BangladeshBLV Ngọc Hoàng(A Cháo)Trực tiếp",
                    "type": "single",
                    "display": "thumbnail-only",
                    "image": {
                        "url": "https://raw.githubusercontent.com/sanghvtac/bonglau/refs/heads/main/thumbs/4a94518fdd31.png",
                        "display": "contain",
                        "padding": 1,
                        "background_color": "#ececec"
                    },
                    "sources": [
                        {
                            "id": "src-4a94518fdd31",
                            "contents": [
                                {
                                    "id": "ct-4a94518fdd31",
                                    "streams": [
                                        {
                                            "stream_links": [
                                                {
                                                    "url": "",
                                                    "type": "hls",
                                                    "request_headers": [
                                                        {
                                                            "key": "Referer",
                                                            "value": "https://sv1.thiendinh.live/xem-truc-tiep/bong-da/friendlies.lfpzLJ0DhW/vietnam-vs-bangladesh.kEVUZXSRSh"
                                                        },
                                                        {
                                                            "key": "User-Agent",
                                                            "value": "Mozilla/5.0"
                                                        }
                                                    ]
                                                }
                                            ]
                                        }
                                    ]
                                }
                            ]
                        }
                    ]
                },
                {
                    "id": "ch-ef1addb71992",
                    "name": "⚽ 17:30 26/03 BLV Táo ChèAsian - VS QualificationAfghanistanKXD0-0---'MyanmarBLV Táo ChèTrực tiếp BLV Táo Chè10:30 26/03Asian Cup - QualificationAfghanistanKXD0-0---'MyanmarBLV Táo ChèTrực tiếp",
                    "type": "single",
                    "display": "thumbnail-only",
                    "image": {
                        "url": "https://raw.githubusercontent.com/sanghvtac/bonglau/refs/heads/main/thumbs/ef1addb71992.png",
                        "display": "contain",
                        "padding": 1,
                        "background_color": "#ececec"
                    },
                    "sources": [
                        {
                            "id": "src-ef1addb71992",
                            "contents": [
                                {
                                    "id": "ct-ef1addb71992",
                                    "streams": [
                                        {
                                            "stream_links": [
                                                {
                                                    "url": "",
                                                    "type": "hls",
                                                    "request_headers": [
                                                        {
                                                            "key": "Referer",
                                                            "value": "https://sv1.thiendinh.live/xem-truc-tiep/bong-da/asian-cup-qualification.yDCAoP1m8s/afghanistan-vs-myanmar.6An-HJpf8s"
                                                        },
                                                        {
                                                            "key": "User-Agent",
                                                            "value": "Mozilla/5.0"
                                                        }
                                                    ]
                                                }
                                            ]
                                        }
                                    ]
                                }
                            ]
                        }
                    ]
                }
            ]
        }
    ]
}